llm_poker/__init__.py
llm_poker/cli.py
llm_poker/environment.py
llm_poker/human_player.py
llm_poker/llm_player.py
llm_poker/player.py
llm_poker/test.py
llm_poker-0.1.14.dist-info/METADATA
llm_poker-0.1.14.dist-info/WHEEL
llm_poker-0.1.14.dist-info/entry_points.txt
llm_poker-0.1.14.dist-info/top_level.txt
llm_poker-0.1.14.dist-info/RECORD
