Metadata-Version: 2.4
Name: llm_poker
Version: 0.1.14
Summary: Texas Hold'em environment with LLM players
Home-page: https://github.com/strangeloopcanon/llm-poker
Author: Rohit Krishnan
Author-email: Rohit Krishnan <rohit.krishnan@gmail.com>
Project-URL: Homepage, https://github.com/strangeloopcanon/llm-poker
Requires-Python: >=3.8
Requires-Dist: llm
Requires-Dist: click
Requires-Dist: pydantic
Dynamic: author
Dynamic: home-page
